umap_jsonl/__init__.py
umap_jsonl/cli.py
umap_jsonl/plotter.py
umap_jsonl/utils.py
umap_jsonl-0.1.0.dist-info/METADATA
umap_jsonl-0.1.0.dist-info/WHEEL
umap_jsonl-0.1.0.dist-info/entry_points.txt
umap_jsonl-0.1.0.dist-info/top_level.txt
umap_jsonl-0.1.0.dist-info/RECORD
